aiohttp_catcher/__init__.py
aiohttp_catcher/canned/__init__.py
aiohttp_catcher/canned/aiohttp_errors.py
aiohttp_catcher/catcher.py
aiohttp_catcher/scenario.py
aiohttp_catcher-0.3.2.dist-info/WHEEL
aiohttp_catcher-0.3.2.dist-info/METADATA
aiohttp_catcher-0.3.2.dist-info/RECORD
