Metadata-Version: 2.1
Name: aiohttp-catcher
Version: 0.3.2
Summary: A centralized error handler for aiohttp servers
Home-page: https://github.com/yuvalherziger/aiohttp-catcher
License: MIT
Keywords: python,python3,aiohttp,error-handling
Author: Yuval Herziger
Author-email: yuvalhrz@gmail.com
Requires-Python: >=3.8,<4.0
Classifier: License :: OSI Approved :: MIT License
Classifier: Programming Language :: Python :: 3
Classifier: Programming Language :: Python :: 3.8
Requires-Dist: aiohttp (>=3.8.1,<4.0.0)
Project-URL: Repository, https://github.com/yuvalherziger/aiohttp-catcher
